tclint/__init__.py
tclint/__main__.py
tclint/_version.py
tclint/checks.py
tclint/comments.py
tclint/config.py
tclint/format.py
tclint/lexer.py
tclint/parser.py
tclint/symbol_table.py
tclint/syntax_tree.py
tclint/violations.py
tclint/cli/tclfmt.py
tclint/cli/tclint.py
tclint/cli/tclsp.py
tclint/cli/utils.py
tclint/commands/__init__.py
tclint/commands/builtin.py
tclint/commands/checks.py
tclint/commands/plugins.py
tclint/commands/schema.py
tclint-0.7.0.dist-info/licenses/LICENSE
tclint-0.7.0.dist-info/METADATA
tclint-0.7.0.dist-info/WHEEL
tclint-0.7.0.dist-info/entry_points.txt
tclint-0.7.0.dist-info/top_level.txt
tclint-0.7.0.dist-info/RECORD
