Metadata-Version: 2.4
Name: tclint
Version: 0.7.0
Summary: A CLI utility for linting and analyzing Tcl code.
Author-email: Noah Moroze <me@noahmoroze.com>
License: MIT License
Requires-Python: >=3.9
License-File: LICENSE
Requires-Dist: ply==3.11
Requires-Dist: tomli~=2.0.1; python_version < "3.11"
Requires-Dist: pathspec==0.11.2
Requires-Dist: importlib-metadata==6.8.0
Requires-Dist: pygls==1.3.1
Requires-Dist: voluptuous==0.15.2
Dynamic: license-file
